/*   1:    */ package nxt;
/*   2:    */ 
/*   3:    */ import java.nio.ByteBuffer;
/*   4:    */ import java.nio.ByteOrder;
/*   5:    */ import java.sql.Connection;
/*   6:    */ import java.sql.PreparedStatement;
/*   7:    */ import java.sql.ResultSet;
/*   8:    */ import java.sql.SQLException;
/*   9:    */ import java.util.ArrayList;
/*  10:    */ import java.util.Iterator;
/*  11:    */ import java.util.LinkedHashMap;
/*  12:    */ import java.util.List;
/*  13:    */ import java.util.Set;
/*  14:    */ import nxt.at.AT_API_Helper;
/*  15:    */ import nxt.at.AT_Constants;
/*  16:    */ import nxt.at.AT_Controller;
/*  17:    */ import nxt.at.AT_Machine_State;
/*  18:    */ import nxt.at.AT_Transaction;
/*  19:    */ import nxt.db.Db;
/*  20:    */ import nxt.db.DbKey;
/*  21:    */ import nxt.db.DbKey.Factory;
/*  22:    */ import nxt.db.DbKey.LongKeyFactory;
/*  23:    */ import nxt.db.DbUtils;
/*  24:    */ import nxt.db.VersionedEntityDbTable;
/*  25:    */ import nxt.util.Listener;
/*  26:    */ 
/*  27:    */ public final class AT
/*  28:    */   extends AT_Machine_State
/*  29:    */ {
/*  30:    */   static
/*  31:    */   {
/*  32: 55 */     Nxt.getBlockchainProcessor().addListener(new Listener()
/*  33:    */     {
/*  34:    */       public void notify(Block paramAnonymousBlock)
/*  35:    */       {
/*  36: 58 */         for (Object localObject1 = AT.pendingFees.keySet().iterator(); ((Iterator)localObject1).hasNext();)
/*  37:    */         {
/*  38: 58 */           localObject2 = (Long)((Iterator)localObject1).next();
/*  39: 59 */           localObject3 = Account.getAccount(((Long)localObject2).longValue());
/*  40: 60 */           ((Account)localObject3).addToBalanceAndUnconfirmedBalanceNQT(-((Long)AT.pendingFees.get(localObject2)).longValue());
/*  41:    */         }
/*  42:    */         Object localObject3;
/*  43: 62 */         localObject1 = new ArrayList();
/*  44: 63 */         for (Object localObject2 = AT.pendingTransactions.iterator(); ((Iterator)localObject2).hasNext();)
/*  45:    */         {
/*  46: 63 */           localObject3 = (AT_Transaction)((Iterator)localObject2).next();
/*  47: 64 */           Account.getAccount(AT_API_Helper.getLong(((AT_Transaction)localObject3).getSenderId())).addToBalanceAndUnconfirmedBalanceNQT(-((AT_Transaction)localObject3).getAmount().longValue());
/*  48: 65 */           Account.addOrGetAccount(AT_API_Helper.getLong(((AT_Transaction)localObject3).getRecipientId())).addToBalanceAndUnconfirmedBalanceNQT(((AT_Transaction)localObject3).getAmount().longValue());
/*  49:    */           
/*  50: 67 */           TransactionImpl.BuilderImpl localBuilderImpl = new TransactionImpl.BuilderImpl((byte)1, Genesis.CREATOR_PUBLIC_KEY, ((AT_Transaction)localObject3).getAmount().longValue(), 0L, paramAnonymousBlock.getTimestamp(), (short)1440, Attachment.AT_PAYMENT);
/*  51:    */           
/*  52:    */ 
/*  53: 70 */           localBuilderImpl.senderId(AT_API_Helper.getLong(((AT_Transaction)localObject3).getSenderId())).recipientId(AT_API_Helper.getLong(((AT_Transaction)localObject3).getRecipientId())).blockId(paramAnonymousBlock.getId()).height(paramAnonymousBlock.getHeight()).blockTimestamp(paramAnonymousBlock.getTimestamp()).ecBlockHeight(0).ecBlockId(0L);
/*  54:    */           
/*  55:    */ 
/*  56:    */ 
/*  57:    */ 
/*  58:    */ 
/*  59:    */ 
/*  60:    */ 
/*  61: 78 */           byte[] arrayOfByte = ((AT_Transaction)localObject3).getMessage();
/*  62: 79 */           if (arrayOfByte != null) {
/*  63: 80 */             localBuilderImpl.message(new Appendix.Message(arrayOfByte));
/*  64:    */           }
/*  65:    */           try
/*  66:    */           {
/*  67: 84 */             TransactionImpl localTransactionImpl = localBuilderImpl.build();
/*  68: 85 */             if (!TransactionDb.hasTransaction(localTransactionImpl.getId())) {
/*  69: 86 */               ((List)localObject1).add(localTransactionImpl);
/*  70:    */             }
/*  71:    */           }
/*  72:    */           catch (NxtException.NotValidException localNotValidException)
/*  73:    */           {
/*  74: 90 */             throw new RuntimeException("Failed to construct AT payment transaction", localNotValidException);
/*  75:    */           }
/*  76:    */         }
/*  77: 94 */         if (((List)localObject1).size() > 0) {
/*  78:    */           try
/*  79:    */           {
/*  80: 95 */             localObject2 = Db.getConnection();localObject3 = null;
/*  81:    */             try
/*  82:    */             {
/*  83: 96 */               TransactionDb.saveTransactions((Connection)localObject2, (List)localObject1);
/*  84:    */             }
/*  85:    */             catch (Throwable localThrowable2)
/*  86:    */             {
/*  87: 95 */               localObject3 = localThrowable2;throw localThrowable2;
/*  88:    */             }
/*  89:    */             finally
/*  90:    */             {
/*  91: 97 */               if (localObject2 != null) {
/*  92: 97 */                 if (localObject3 != null) {
/*  93:    */                   try
/*  94:    */                   {
/*  95: 97 */                     ((Connection)localObject2).close();
/*  96:    */                   }
/*  97:    */                   catch (Throwable localThrowable3)
/*  98:    */                   {
/*  99: 97 */                     ((Throwable)localObject3).addSuppressed(localThrowable3);
/* 100:    */                   }
/* 101:    */                 } else {
/* 102: 97 */                   ((Connection)localObject2).close();
/* 103:    */                 }
/* 104:    */               }
/* 105:    */             }
/* 106:    */           }
/* 107:    */           catch (SQLException localSQLException)
/* 108:    */           {
/* 109: 99 */             throw new RuntimeException(localSQLException.toString(), localSQLException);
/* 110:    */           }
/* 111:    */         }
/* 112:    */       }
/* 113: 99 */     }, BlockchainProcessor.Event.AFTER_BLOCK_APPLY);
/* 114:    */   }
/* 115:    */   
/* 116:108 */   private static final LinkedHashMap<Long, Long> pendingFees = new LinkedHashMap();
/* 117:109 */   private static final List<AT_Transaction> pendingTransactions = new ArrayList();
/* 118:    */   
/* 119:    */   public static void clearPendingFees()
/* 120:    */   {
/* 121:112 */     pendingFees.clear();
/* 122:    */   }
/* 123:    */   
/* 124:    */   public static void clearPendingTransactions()
/* 125:    */   {
/* 126:116 */     pendingTransactions.clear();
/* 127:    */   }
/* 128:    */   
/* 129:    */   public static void addPendingFee(long paramLong1, long paramLong2)
/* 130:    */   {
/* 131:120 */     pendingFees.put(Long.valueOf(paramLong1), Long.valueOf(paramLong2));
/* 132:    */   }
/* 133:    */   
/* 134:    */   public static void addPendingFee(byte[] paramArrayOfByte, long paramLong)
/* 135:    */   {
/* 136:124 */     addPendingFee(AT_API_Helper.getLong(paramArrayOfByte), paramLong);
/* 137:    */   }
/* 138:    */   
/* 139:    */   public static void addPendingTransaction(AT_Transaction paramAT_Transaction)
/* 140:    */   {
/* 141:128 */     pendingTransactions.add(paramAT_Transaction);
/* 142:    */   }
/* 143:    */   
/* 144:    */   public static class ATState
/* 145:    */   {
/* 146:    */     private final long atId;
/* 147:    */     private final DbKey dbKey;
/* 148:    */     private byte[] state;
/* 149:    */     private int prevHeight;
/* 150:    */     private int nextHeight;
/* 151:    */     private int sleepBetween;
/* 152:    */     private long prevBalance;
/* 153:    */     private boolean freezeWhenSameBalance;
/* 154:    */     private long minActivationAmount;
/* 155:    */     
/* 156:    */     private ATState(long paramLong1, byte[] paramArrayOfByte, int paramInt1, int paramInt2, int paramInt3, long paramLong2, boolean paramBoolean, long paramLong3)
/* 157:    */     {
/* 158:144 */       this.atId = paramLong1;
/* 159:145 */       this.dbKey = AT.atStateDbKeyFactory.newKey(this.atId);
/* 160:146 */       this.state = paramArrayOfByte;
/* 161:147 */       this.nextHeight = paramInt2;
/* 162:148 */       this.sleepBetween = paramInt3;
/* 163:149 */       this.prevBalance = paramLong2;
/* 164:150 */       this.freezeWhenSameBalance = paramBoolean;
/* 165:151 */       this.minActivationAmount = paramLong3;
/* 166:    */     }
/* 167:    */     
/* 168:    */     private ATState(ResultSet paramResultSet)
/* 169:    */       throws SQLException
/* 170:    */     {
/* 171:155 */       this.atId = paramResultSet.getLong("at_id");
/* 172:156 */       this.dbKey = AT.atStateDbKeyFactory.newKey(this.atId);
/* 173:157 */       this.state = paramResultSet.getBytes("state");
/* 174:158 */       this.prevHeight = paramResultSet.getInt("prev_height");
/* 175:159 */       this.nextHeight = paramResultSet.getInt("next_height");
/* 176:160 */       this.sleepBetween = paramResultSet.getInt("sleep_between");
/* 177:161 */       this.prevBalance = paramResultSet.getLong("prev_balance");
/* 178:162 */       this.freezeWhenSameBalance = paramResultSet.getBoolean("freeze_when_same_balance");
/* 179:163 */       this.minActivationAmount = paramResultSet.getLong("min_activate_amount");
/* 180:    */     }
/* 181:    */     
/* 182:    */     private void save(Connection paramConnection)
/* 183:    */       throws SQLException
/* 184:    */     {
/* 185:167 */       PreparedStatement localPreparedStatement = paramConnection.prepareStatement("MERGE INTO at_state (at_id, state, prev_height ,next_height, sleep_between, prev_balance, freeze_when_same_balance, min_activate_amount, height, latest) KEY (at_id, height) VALUES (?, ?, ?, ?, ?, ?, ?, ?, ?, TRUE)");Object localObject1 = null;
/* 186:    */       try
/* 187:    */       {
/* 188:170 */         int i = 0;
/* 189:171 */         localPreparedStatement.setLong(++i, this.atId);
/* 190:    */         
/* 191:173 */         DbUtils.setBytes(localPreparedStatement, ++i, AT.compressState(this.state));
/* 192:174 */         localPreparedStatement.setInt(++i, this.prevHeight);
/* 193:175 */         localPreparedStatement.setInt(++i, this.nextHeight);
/* 194:176 */         localPreparedStatement.setInt(++i, this.sleepBetween);
/* 195:177 */         localPreparedStatement.setLong(++i, this.prevBalance);
/* 196:178 */         localPreparedStatement.setBoolean(++i, this.freezeWhenSameBalance);
/* 197:179 */         localPreparedStatement.setLong(++i, this.minActivationAmount);
/* 198:180 */         localPreparedStatement.setInt(++i, Nxt.getBlockchain().getHeight());
/* 199:181 */         localPreparedStatement.executeUpdate();
/* 200:    */       }
/* 201:    */       catch (Throwable localThrowable2)
/* 202:    */       {
/* 203:167 */         localObject1 = localThrowable2;throw localThrowable2;
/* 204:    */       }
/* 205:    */       finally
/* 206:    */       {
/* 207:182 */         if (localPreparedStatement != null) {
/* 208:182 */           if (localObject1 != null) {
/* 209:    */             try
/* 210:    */             {
/* 211:182 */               localPreparedStatement.close();
/* 212:    */             }
/* 213:    */             catch (Throwable localThrowable3)
/* 214:    */             {
/* 215:182 */               ((Throwable)localObject1).addSuppressed(localThrowable3);
/* 216:    */             }
/* 217:    */           } else {
/* 218:182 */             localPreparedStatement.close();
/* 219:    */           }
/* 220:    */         }
/* 221:    */       }
/* 222:    */     }
/* 223:    */     
/* 224:    */     public long getATId()
/* 225:    */     {
/* 226:186 */       return this.atId;
/* 227:    */     }
/* 228:    */     
/* 229:    */     public byte[] getState()
/* 230:    */     {
/* 231:190 */       return this.state;
/* 232:    */     }
/* 233:    */     
/* 234:    */     public int getPrevHeight()
/* 235:    */     {
/* 236:194 */       return this.prevHeight;
/* 237:    */     }
/* 238:    */     
/* 239:    */     public int getNextHeight()
/* 240:    */     {
/* 241:198 */       return this.nextHeight;
/* 242:    */     }
/* 243:    */     
/* 244:    */     public int getSleepBetween()
/* 245:    */     {
/* 246:202 */       return this.sleepBetween;
/* 247:    */     }
/* 248:    */     
/* 249:    */     public long getPrevBalance()
/* 250:    */     {
/* 251:206 */       return this.prevBalance;
/* 252:    */     }
/* 253:    */     
/* 254:    */     public boolean getFreezeWhenSameBalance()
/* 255:    */     {
/* 256:210 */       return this.freezeWhenSameBalance;
/* 257:    */     }
/* 258:    */     
/* 259:    */     public long getMinActivationAmount()
/* 260:    */     {
/* 261:214 */       return this.minActivationAmount;
/* 262:    */     }
/* 263:    */     
/* 264:    */     public void setState(byte[] paramArrayOfByte)
/* 265:    */     {
/* 266:218 */       this.state = paramArrayOfByte;
/* 267:    */     }
/* 268:    */     
/* 269:    */     public void setPrevHeight(int paramInt)
/* 270:    */     {
/* 271:222 */       this.prevHeight = paramInt;
/* 272:    */     }
/* 273:    */     
/* 274:    */     public void setNextHeight(int paramInt)
/* 275:    */     {
/* 276:226 */       this.nextHeight = paramInt;
/* 277:    */     }
/* 278:    */     
/* 279:    */     public void setSleepBetween(int paramInt)
/* 280:    */     {
/* 281:230 */       this.sleepBetween = paramInt;
/* 282:    */     }
/* 283:    */     
/* 284:    */     public void setPrevBalance(long paramLong)
/* 285:    */     {
/* 286:234 */       this.prevBalance = paramLong;
/* 287:    */     }
/* 288:    */     
/* 289:    */     public void setFreezeWhenSameBalance(boolean paramBoolean)
/* 290:    */     {
/* 291:238 */       this.freezeWhenSameBalance = paramBoolean;
/* 292:    */     }
/* 293:    */     
/* 294:    */     public void setMinActivationAmount(long paramLong)
/* 295:    */     {
/* 296:242 */       this.minActivationAmount = paramLong;
/* 297:    */     }
/* 298:    */   }
/* 299:    */   
/* 300:246 */   private static final DbKey.LongKeyFactory<AT> atDbKeyFactory = new DbKey.LongKeyFactory("id")
/* 301:    */   {
/* 302:    */     public DbKey newKey(AT paramAnonymousAT)
/* 303:    */     {
/* 304:249 */       return paramAnonymousAT.dbKey;
/* 305:    */     }
/* 306:    */   };
/* 307:253 */   private static final VersionedEntityDbTable<AT> atTable = new VersionedEntityDbTable("at", atDbKeyFactory)
/* 308:    */   {
/* 309:    */     protected AT load(Connection paramAnonymousConnection, ResultSet paramAnonymousResultSet)
/* 310:    */       throws SQLException
/* 311:    */     {
/* 312:257 */       throw new RuntimeException("AT attempted to be created with atTable.load");
/* 313:    */     }
/* 314:    */     
/* 315:    */     protected void save(Connection paramAnonymousConnection, AT paramAnonymousAT)
/* 316:    */       throws SQLException
/* 317:    */     {
/* 318:261 */       paramAnonymousAT.save(paramAnonymousConnection);
/* 319:    */     }
/* 320:    */     
/* 321:    */     protected String defaultSort()
/* 322:    */     {
/* 323:265 */       return " ORDER BY id ";
/* 324:    */     }
/* 325:    */   };
/* 326:269 */   private static final DbKey.LongKeyFactory<ATState> atStateDbKeyFactory = new DbKey.LongKeyFactory("at_id")
/* 327:    */   {
/* 328:    */     public DbKey newKey(AT.ATState paramAnonymousATState)
/* 329:    */     {
/* 330:272 */       return paramAnonymousATState.dbKey;
/* 331:    */     }
/* 332:    */   };
/* 333:276 */   private static final VersionedEntityDbTable<ATState> atStateTable = new VersionedEntityDbTable("at_state", atStateDbKeyFactory)
/* 334:    */   {
/* 335:    */     protected AT.ATState load(Connection paramAnonymousConnection, ResultSet paramAnonymousResultSet)
/* 336:    */       throws SQLException
/* 337:    */     {
/* 338:279 */       return new AT.ATState(paramAnonymousResultSet, null);
/* 339:    */     }
/* 340:    */     
/* 341:    */     protected void save(Connection paramAnonymousConnection, AT.ATState paramAnonymousATState)
/* 342:    */       throws SQLException
/* 343:    */     {
/* 344:283 */       paramAnonymousATState.save(paramAnonymousConnection);
/* 345:    */     }
/* 346:    */     
/* 347:    */     protected String defaultSort()
/* 348:    */     {
/* 349:287 */       return " ORDER BY prev_height, height, at_id ";
/* 350:    */     }
/* 351:    */   };
/* 352:    */   private final String name;
/* 353:    */   private final String description;
/* 354:    */   private final DbKey dbKey;
/* 355:    */   private final int nextHeight;
/* 356:    */   
/* 357:    */   public static AT getAT(byte[] paramArrayOfByte)
/* 358:    */   {
/* 359:310 */     return getAT(Long.valueOf(AT_API_Helper.getLong(paramArrayOfByte)));
/* 360:    */   }
/* 361:    */   
/* 362:    */   static void addAT(Long paramLong1, Long paramLong2, String paramString1, String paramString2, byte[] paramArrayOfByte, int paramInt)
/* 363:    */   {
/* 364:359 */     ByteBuffer localByteBuffer = ByteBuffer.allocate(16);
/* 365:360 */     localByteBuffer.order(ByteOrder.LITTLE_ENDIAN);
/* 366:    */     
/* 367:362 */     localByteBuffer.putLong(paramLong1.longValue());
/* 368:    */     
/* 369:364 */     byte[] arrayOfByte1 = new byte[8];
/* 370:    */     
/* 371:366 */     localByteBuffer.putLong(8, paramLong2.longValue());
/* 372:    */     
/* 373:368 */     byte[] arrayOfByte2 = new byte[8];
/* 374:369 */     localByteBuffer.clear();
/* 375:370 */     localByteBuffer.get(arrayOfByte1, 0, 8);
/* 376:371 */     localByteBuffer.get(arrayOfByte2, 0, 8);
/* 377:    */     
/* 378:373 */     AT localAT = new AT(arrayOfByte1, arrayOfByte2, paramString1, paramString2, paramArrayOfByte, paramInt);
/* 379:    */     
/* 380:375 */     AT_Controller.resetMachine(localAT);
/* 381:    */     
/* 382:377 */     atTable.insert(localAT);
/* 383:    */     
/* 384:379 */     localAT.saveState();
/* 385:    */     
/* 386:381 */     Account localAccount = Account.addOrGetAccount(paramLong1.longValue());
/* 387:382 */     localAccount.apply(new byte[32], paramInt);
/* 388:    */   }
/* 389:    */   
/* 390:    */   public void saveState()
/* 391:    */   {
/* 392:386 */     ATState localATState = (ATState)atStateTable.get(atStateDbKeyFactory.newKey(AT_API_Helper.getLong(getId())));
/* 393:387 */     int i = Nxt.getBlockchain().getHeight();
/* 394:388 */     int j = i + getWaitForNumberOfBlocks();
/* 395:389 */     if (localATState != null)
/* 396:    */     {
/* 397:390 */       localATState.setState(getState());
/* 398:391 */       localATState.setPrevHeight(i);
/* 399:392 */       localATState.setNextHeight(j);
/* 400:393 */       localATState.setSleepBetween(getSleepBetween());
/* 401:394 */       localATState.setPrevBalance(getP_balance().longValue());
/* 402:395 */       localATState.setFreezeWhenSameBalance(freezeOnSameBalance());
/* 403:396 */       localATState.setMinActivationAmount(minActivationAmount());
/* 404:    */     }
/* 405:    */     else
/* 406:    */     {
/* 407:399 */       localATState = new ATState(AT_API_Helper.getLong(getId()), getState(), i, j, getSleepBetween(), getP_balance().longValue(), freezeOnSameBalance(), minActivationAmount(), null);
/* 408:    */     }
/* 409:401 */     atStateTable.insert(localATState);
/* 410:    */   }
/* 411:    */   
/* 412:    */   private static List<AT> createATs(ResultSet paramResultSet)
/* 413:    */     throws SQLException
/* 414:    */   {
/* 415:406 */     ArrayList localArrayList = new ArrayList();
/* 416:407 */     while (paramResultSet.next())
/* 417:    */     {
/* 418:409 */       int i = 0;
/* 419:410 */       Long localLong1 = Long.valueOf(paramResultSet.getLong(++i));
/* 420:411 */       Long localLong2 = Long.valueOf(paramResultSet.getLong(++i));
/* 421:412 */       String str1 = paramResultSet.getString(++i);
/* 422:413 */       String str2 = paramResultSet.getString(++i);
/* 423:414 */       short s = paramResultSet.getShort(++i);
/* 424:415 */       byte[] arrayOfByte1 = decompressState(paramResultSet.getBytes(++i));
/* 425:416 */       int j = paramResultSet.getInt(++i);
/* 426:417 */       int k = paramResultSet.getInt(++i);
/* 427:418 */       int m = paramResultSet.getInt(++i);
/* 428:419 */       int n = paramResultSet.getInt(++i);
/* 429:420 */       int i1 = paramResultSet.getInt(++i);
/* 430:421 */       int i2 = paramResultSet.getInt(++i);
/* 431:422 */       int i3 = paramResultSet.getInt(++i);
/* 432:423 */       boolean bool = paramResultSet.getBoolean(++i);
/* 433:424 */       long l = paramResultSet.getLong(++i);
/* 434:425 */       byte[] arrayOfByte2 = decompressState(paramResultSet.getBytes(++i));
/* 435:    */       
/* 436:427 */       AT localAT = new AT(AT_API_Helper.getByteArray(localLong1.longValue()), AT_API_Helper.getByteArray(localLong2.longValue()), str1, str2, s, arrayOfByte1, j, k, m, n, i1, i2, i3, bool, l, arrayOfByte2);
/* 437:    */       
/* 438:    */ 
/* 439:430 */       localArrayList.add(localAT);
/* 440:    */     }
/* 441:433 */     return localArrayList;
/* 442:    */   }
/* 443:    */   
/* 444:    */   private void save(Connection paramConnection)
/* 445:    */   {
/* 446:    */     try
/* 447:    */     {
/* 448:438 */       PreparedStatement localPreparedStatement = paramConnection.prepareStatement("INSERT INTO at (id , creator_id , name , description , version , csize , dsize , c_user_stack_bytes , c_call_stack_bytes , creation_height , ap_code , height) VALUES (?, ?, ?, ?, ?, ?, ?, ?, ?, ?, ?, ?)");Object localObject1 = null;
/* 449:    */       try
/* 450:    */       {
/* 451:444 */         int i = 0;
/* 452:445 */         localPreparedStatement.setLong(++i, AT_API_Helper.getLong(getId()));
/* 453:446 */         localPreparedStatement.setLong(++i, AT_API_Helper.getLong(getCreator()));
/* 454:447 */         DbUtils.setString(localPreparedStatement, ++i, getName());
/* 455:448 */         DbUtils.setString(localPreparedStatement, ++i, getDescription());
/* 456:449 */         localPreparedStatement.setShort(++i, getVersion());
/* 457:450 */         localPreparedStatement.setInt(++i, getCsize());
/* 458:451 */         localPreparedStatement.setInt(++i, getDsize());
/* 459:452 */         localPreparedStatement.setInt(++i, getC_user_stack_bytes());
/* 460:453 */         localPreparedStatement.setInt(++i, getC_call_stack_bytes());
/* 461:454 */         localPreparedStatement.setInt(++i, getCreationBlockHeight());
/* 462:    */         
/* 463:456 */         DbUtils.setBytes(localPreparedStatement, ++i, compressState(getApCode()));
/* 464:457 */         localPreparedStatement.setInt(++i, Nxt.getBlockchain().getHeight());
/* 465:    */         
/* 466:459 */         localPreparedStatement.executeUpdate();
/* 467:    */       }
/* 468:    */       catch (Throwable localThrowable2)
/* 469:    */       {
/* 470:438 */         localObject1 = localThrowable2;throw localThrowable2;
/* 471:    */       }
/* 472:    */       finally
/* 473:    */       {
/* 474:460 */         if (localPreparedStatement != null) {
/* 475:460 */           if (localObject1 != null) {
/* 476:    */             try
/* 477:    */             {
/* 478:460 */               localPreparedStatement.close();
/* 479:    */             }
/* 480:    */             catch (Throwable localThrowable3)
/* 481:    */             {
/* 482:460 */               ((Throwable)localObject1).addSuppressed(localThrowable3);
/* 483:    */             }
/* 484:    */           } else {
/* 485:460 */             localPreparedStatement.close();
/* 486:    */           }
/* 487:    */         }
/* 488:    */       }
/* 489:    */     }
/* 490:    */     catch (SQLException localSQLException)
/* 491:    */     {
/* 492:462 */       throw new RuntimeException(localSQLException.toString(), localSQLException);
/* 493:    */     }
/* 494:    */   }
/* 495:    */   
/* 496:    */   private static void deleteAT(AT paramAT)
/* 497:    */   {
/* 498:469 */     ATState localATState = (ATState)atStateTable.get(atStateDbKeyFactory.newKey(AT_API_Helper.getLong(paramAT.getId())));
/* 499:470 */     if (localATState != null) {
/* 500:471 */       atStateTable.delete(localATState);
/* 501:    */     }
/* 502:473 */     atTable.delete(paramAT);
/* 503:    */   }
/* 504:    */   
/* 505:    */   private static void deleteAT(Long paramLong)
/* 506:    */   {
/* 507:479 */     AT localAT = getAT(paramLong);
/* 508:480 */     if (localAT != null) {
/* 509:481 */       deleteAT(localAT);
/* 510:    */     }
/* 511:    */   }
/* 512:    */   
/* 513:    */   public static List<Long> getOrderedATs()
/* 514:    */   {
/* 515:487 */     ArrayList localArrayList = new ArrayList();
/* 516:    */     try
/* 517:    */     {
/* 518:488 */       Connection localConnection = Db.getConnection();Object localObject1 = null;
/* 519:    */       try
/* 520:    */       {
/* 521:489 */         PreparedStatement localPreparedStatement = localConnection.prepareStatement("SELECT at.id FROM at INNER JOIN at_state ON at.id = at_state.at_id INNER JOIN account ON at.id = account.id WHERE at.latest = TRUE AND at_state.latest = TRUE AND account.latest = TRUE AND at_state.next_height <= ? AND account.balance >= ? AND (at_state.freeze_when_same_balance = FALSE OR (account.balance - at_state.prev_balance >= at_state.min_activate_amount)) ORDER BY at_state.prev_height, at_state.next_height, at.id");Object localObject2 = null;
/* 522:    */         try
/* 523:    */         {
/* 524:496 */           localPreparedStatement.setInt(1, Nxt.getBlockchain().getHeight() + 1);
/* 525:497 */           localPreparedStatement.setLong(2, AT_Constants.getInstance().STEP_FEE(Nxt.getBlockchain().getHeight()) * AT_Constants.getInstance().API_STEP_MULTIPLIER(Nxt.getBlockchain().getHeight()));
/* 526:    */           
/* 527:499 */           ResultSet localResultSet = localPreparedStatement.executeQuery();
/* 528:500 */           while (localResultSet.next())
/* 529:    */           {
/* 530:502 */             Long localLong = Long.valueOf(localResultSet.getLong(1));
/* 531:503 */             localArrayList.add(localLong);
/* 532:    */           }
/* 533:    */         }
/* 534:    */         catch (Throwable localThrowable4)
/* 535:    */         {
/* 536:488 */           localObject2 = localThrowable4;throw localThrowable4;
/* 537:    */         }
/* 538:    */         finally {}
/* 539:    */       }
/* 540:    */       catch (Throwable localThrowable2)
/* 541:    */       {
/* 542:488 */         localObject1 = localThrowable2;throw localThrowable2;
/* 543:    */       }
/* 544:    */       finally
/* 545:    */       {
/* 546:505 */         if (localConnection != null) {
/* 547:505 */           if (localObject1 != null) {
/* 548:    */             try
/* 549:    */             {
/* 550:505 */               localConnection.close();
/* 551:    */             }
/* 552:    */             catch (Throwable localThrowable6)
/* 553:    */             {
/* 554:505 */               ((Throwable)localObject1).addSuppressed(localThrowable6);
/* 555:    */             }
/* 556:    */           } else {
/* 557:505 */             localConnection.close();
/* 558:    */           }
/* 559:    */         }
/* 560:    */       }
/* 561:    */     }
/* 562:    */     catch (SQLException localSQLException)
/* 563:    */     {
/* 564:507 */       throw new RuntimeException(localSQLException.toString(), localSQLException);
/* 565:    */     }
/* 566:509 */     return localArrayList;
/* 567:    */   }
/* 568:    */   
/* 569:    */   private AT(byte[] paramArrayOfByte1, byte[] paramArrayOfByte2, String paramString1, String paramString2, byte[] paramArrayOfByte3, int paramInt)
/* 570:    */   {
/* 571:571 */     super(paramArrayOfByte1, paramArrayOfByte2, paramArrayOfByte3, paramInt);
/* 572:572 */     this.name = paramString1;
/* 573:573 */     this.description = paramString2;
/* 574:574 */     this.dbKey = atDbKeyFactory.newKey(AT_API_Helper.getLong(paramArrayOfByte1));
/* 575:575 */     this.nextHeight = Nxt.getBlockchain().getHeight();
/* 576:    */   }
/* 577:    */   
/* 578:    */   public AT(byte[] paramArrayOfByte1, byte[] paramArrayOfByte2, String paramString1, String paramString2, short paramShort, byte[] paramArrayOfByte3, int paramInt1, int paramInt2, int paramInt3, int paramInt4, int paramInt5, int paramInt6, int paramInt7, boolean paramBoolean, long paramLong, byte[] paramArrayOfByte4)
/* 579:    */   {
/* 580:583 */     super(paramArrayOfByte1, paramArrayOfByte2, paramShort, paramArrayOfByte3, paramInt1, paramInt2, paramInt3, paramInt4, paramInt5, paramInt6, paramBoolean, paramLong, paramArrayOfByte4);
/* 581:    */     
/* 582:    */ 
/* 583:    */ 
/* 584:587 */     this.name = paramString1;
/* 585:588 */     this.description = paramString2;
/* 586:589 */     this.dbKey = atDbKeyFactory.newKey(AT_API_Helper.getLong(paramArrayOfByte1));
/* 587:590 */     this.nextHeight = paramInt7;
/* 588:    */   }
/* 589:    */   
/* 590:    */   public String getName()
/* 591:    */   {
/* 592:594 */     return this.name;
/* 593:    */   }
/* 594:    */   
/* 595:    */   public String getDescription()
/* 596:    */   {
/* 597:598 */     return this.description;
/* 598:    */   }
/* 599:    */   
/* 600:    */   public int nextHeight()
/* 601:    */   {
/* 602:602 */     return this.nextHeight;
/* 603:    */   }
/* 604:    */   
/* 605:    */   public byte[] getApCode()
/* 606:    */   {
/* 607:606 */     return getAp_code().array();
/* 608:    */   }
/* 609:    */   
/* 610:    */   public byte[] getApData()
/* 611:    */   {
/* 612:610 */     return getAp_data().array();
/* 613:    */   }
/* 614:    */   
/* 615:    */   /* Error */
/* 616:    */   public static java.util.Collection<Long> getAllATIds()
/* 617:    */   {
/* 618:    */     // Byte code:
/* 619:    */     //   0: invokestatic 14	nxt/db/Db:getConnection	()Ljava/sql/Connection;
/* 620:    */     //   3: ldc 15
/* 621:    */     //   5: invokeinterface 16 2 0
/* 622:    */     //   10: astore_0
/* 623:    */     //   11: aconst_null
/* 624:    */     //   12: astore_1
/* 625:    */     //   13: aload_0
/* 626:    */     //   14: invokeinterface 17 1 0
/* 627:    */     //   19: astore_2
/* 628:    */     //   20: new 18	java/util/ArrayList
/* 629:    */     //   23: dup
/* 630:    */     //   24: invokespecial 19	java/util/ArrayList:<init>	()V
/* 631:    */     //   27: astore_3
/* 632:    */     //   28: aload_2
/* 633:    */     //   29: invokeinterface 20 1 0
/* 634:    */     //   34: ifeq +24 -> 58
/* 635:    */     //   37: aload_3
/* 636:    */     //   38: aload_2
/* 637:    */     //   39: ldc 21
/* 638:    */     //   41: invokeinterface 22 2 0
/* 639:    */     //   46: invokestatic 9	java/lang/Long:valueOf	(J)Ljava/lang/Long;
/* 640:    */     //   49: invokeinterface 13 2 0
/* 641:    */     //   54: pop
/* 642:    */     //   55: goto -27 -> 28
/* 643:    */     //   58: aload_3
/* 644:    */     //   59: astore 4
/* 645:    */     //   61: aload_0
/* 646:    */     //   62: ifnull +33 -> 95
/* 647:    */     //   65: aload_1
/* 648:    */     //   66: ifnull +23 -> 89
/* 649:    */     //   69: aload_0
/* 650:    */     //   70: invokeinterface 23 1 0
/* 651:    */     //   75: goto +20 -> 95
/* 652:    */     //   78: astore 5
/* 653:    */     //   80: aload_1
/* 654:    */     //   81: aload 5
/* 655:    */     //   83: invokevirtual 25	java/lang/Throwable:addSuppressed	(Ljava/lang/Throwable;)V
/* 656:    */     //   86: goto +9 -> 95
/* 657:    */     //   89: aload_0
/* 658:    */     //   90: invokeinterface 23 1 0
/* 659:    */     //   95: aload 4
/* 660:    */     //   97: areturn
/* 661:    */     //   98: astore_2
/* 662:    */     //   99: aload_2
/* 663:    */     //   100: astore_1
/* 664:    */     //   101: aload_2
/* 665:    */     //   102: athrow
/* 666:    */     //   103: astore 6
/* 667:    */     //   105: aload_0
/* 668:    */     //   106: ifnull +33 -> 139
/* 669:    */     //   109: aload_1
/* 670:    */     //   110: ifnull +23 -> 133
/* 671:    */     //   113: aload_0
/* 672:    */     //   114: invokeinterface 23 1 0
/* 673:    */     //   119: goto +20 -> 139
/* 674:    */     //   122: astore 7
/* 675:    */     //   124: aload_1
/* 676:    */     //   125: aload 7
/* 677:    */     //   127: invokevirtual 25	java/lang/Throwable:addSuppressed	(Ljava/lang/Throwable;)V
/* 678:    */     //   130: goto +9 -> 139
/* 679:    */     //   133: aload_0
/* 680:    */     //   134: invokeinterface 23 1 0
/* 681:    */     //   139: aload 6
/* 682:    */     //   141: athrow
/* 683:    */     //   142: astore_0
/* 684:    */     //   143: new 27	java/lang/RuntimeException
/* 685:    */     //   146: dup
/* 686:    */     //   147: aload_0
/* 687:    */     //   148: invokevirtual 28	java/sql/SQLException:toString	()Ljava/lang/String;
/* 688:    */     //   151: aload_0
/* 689:    */     //   152: invokespecial 29	java/lang/RuntimeException:<init>	(Ljava/lang/String;Ljava/lang/Throwable;)V
/* 690:    */     //   155: athrow
/* 691:    */     // Line number table:
/* 692:    */     //   Java source line #294	-> byte code offset #0
/* 693:    */     //   Java source line #296	-> byte code offset #13
/* 694:    */     //   Java source line #297	-> byte code offset #20
/* 695:    */     //   Java source line #298	-> byte code offset #28
/* 696:    */     //   Java source line #299	-> byte code offset #37
/* 697:    */     //   Java source line #301	-> byte code offset #58
/* 698:    */     //   Java source line #302	-> byte code offset #61
/* 699:    */     //   Java source line #294	-> byte code offset #98
/* 700:    */     //   Java source line #302	-> byte code offset #103
/* 701:    */     //   Java source line #303	-> byte code offset #142
/* 702:    */     //   Java source line #304	-> byte code offset #143
/* 703:    */     // Local variable table:
/* 704:    */     //   start	length	slot	name	signature
/* 705:    */     //   10	124	0	localPreparedStatement	PreparedStatement
/* 706:    */     //   142	10	0	localSQLException	SQLException
/* 707:    */     //   12	113	1	localObject1	Object
/* 708:    */     //   19	20	2	localResultSet	ResultSet
/* 709:    */     //   98	4	2	localThrowable1	Throwable
/* 710:    */     //   27	32	3	localArrayList1	ArrayList
/* 711:    */     //   78	4	5	localThrowable2	Throwable
/* 712:    */     //   103	37	6	localObject2	Object
/* 713:    */     //   122	4	7	localThrowable3	Throwable
/* 714:    */     // Exception table:
/* 715:    */     //   from	to	target	type
/* 716:    */     //   69	75	78	java/lang/Throwable
/* 717:    */     //   13	61	98	java/lang/Throwable
/* 718:    */     //   13	61	103	finally
/* 719:    */     //   98	105	103	finally
/* 720:    */     //   113	119	122	java/lang/Throwable
/* 721:    */     //   0	95	142	java/sql/SQLException
/* 722:    */     //   98	142	142	java/sql/SQLException
/* 723:    */   }
/* 724:    */   
/* 725:    */   /* Error */
/* 726:    */   public static AT getAT(Long paramLong)
/* 727:    */   {
/* 728:    */     // Byte code:
/* 729:    */     //   0: invokestatic 14	nxt/db/Db:getConnection	()Ljava/sql/Connection;
/* 730:    */     //   3: astore_1
/* 731:    */     //   4: aconst_null
/* 732:    */     //   5: astore_2
/* 733:    */     //   6: aload_1
/* 734:    */     //   7: ldc 31
/* 735:    */     //   9: invokeinterface 16 2 0
/* 736:    */     //   14: astore_3
/* 737:    */     //   15: aconst_null
/* 738:    */     //   16: astore 4
/* 739:    */     //   18: iconst_0
/* 740:    */     //   19: istore 5
/* 741:    */     //   21: aload_3
/* 742:    */     //   22: iinc 5 1
/* 743:    */     //   25: iload 5
/* 744:    */     //   27: aload_0
/* 745:    */     //   28: invokevirtual 32	java/lang/Long:longValue	()J
/* 746:    */     //   31: invokeinterface 33 4 0
/* 747:    */     //   36: aload_3
/* 748:    */     //   37: invokeinterface 17 1 0
/* 749:    */     //   42: astore 6
/* 750:    */     //   44: aload 6
/* 751:    */     //   46: invokestatic 34	nxt/AT:createATs	(Ljava/sql/ResultSet;)Ljava/util/List;
/* 752:    */     //   49: astore 7
/* 753:    */     //   51: aload 7
/* 754:    */     //   53: invokeinterface 35 1 0
/* 755:    */     //   58: ifle +89 -> 147
/* 756:    */     //   61: aload 7
/* 757:    */     //   63: iconst_0
/* 758:    */     //   64: invokeinterface 36 2 0
/* 759:    */     //   69: checkcast 37	nxt/AT
/* 760:    */     //   72: astore 8
/* 761:    */     //   74: aload_3
/* 762:    */     //   75: ifnull +35 -> 110
/* 763:    */     //   78: aload 4
/* 764:    */     //   80: ifnull +24 -> 104
/* 765:    */     //   83: aload_3
/* 766:    */     //   84: invokeinterface 23 1 0
/* 767:    */     //   89: goto +21 -> 110
/* 768:    */     //   92: astore 9
/* 769:    */     //   94: aload 4
/* 770:    */     //   96: aload 9
/* 771:    */     //   98: invokevirtual 25	java/lang/Throwable:addSuppressed	(Ljava/lang/Throwable;)V
/* 772:    */     //   101: goto +9 -> 110
/* 773:    */     //   104: aload_3
/* 774:    */     //   105: invokeinterface 23 1 0
/* 775:    */     //   110: aload_1
/* 776:    */     //   111: ifnull +33 -> 144
/* 777:    */     //   114: aload_2
/* 778:    */     //   115: ifnull +23 -> 138
/* 779:    */     //   118: aload_1
/* 780:    */     //   119: invokeinterface 38 1 0
/* 781:    */     //   124: goto +20 -> 144
/* 782:    */     //   127: astore 9
/* 783:    */     //   129: aload_2
/* 784:    */     //   130: aload 9
/* 785:    */     //   132: invokevirtual 25	java/lang/Throwable:addSuppressed	(Ljava/lang/Throwable;)V
/* 786:    */     //   135: goto +9 -> 144
/* 787:    */     //   138: aload_1
/* 788:    */     //   139: invokeinterface 38 1 0
/* 789:    */     //   144: aload 8
/* 790:    */     //   146: areturn
/* 791:    */     //   147: aconst_null
/* 792:    */     //   148: astore 8
/* 793:    */     //   150: aload_3
/* 794:    */     //   151: ifnull +35 -> 186
/* 795:    */     //   154: aload 4
/* 796:    */     //   156: ifnull +24 -> 180
/* 797:    */     //   159: aload_3
/* 798:    */     //   160: invokeinterface 23 1 0
/* 799:    */     //   165: goto +21 -> 186
/* 800:    */     //   168: astore 9
/* 801:    */     //   170: aload 4
/* 802:    */     //   172: aload 9
/* 803:    */     //   174: invokevirtual 25	java/lang/Throwable:addSuppressed	(Ljava/lang/Throwable;)V
/* 804:    */     //   177: goto +9 -> 186
/* 805:    */     //   180: aload_3
/* 806:    */     //   181: invokeinterface 23 1 0
/* 807:    */     //   186: aload_1
/* 808:    */     //   187: ifnull +33 -> 220
/* 809:    */     //   190: aload_2
/* 810:    */     //   191: ifnull +23 -> 214
/* 811:    */     //   194: aload_1
/* 812:    */     //   195: invokeinterface 38 1 0
/* 813:    */     //   200: goto +20 -> 220
/* 814:    */     //   203: astore 9
/* 815:    */     //   205: aload_2
/* 816:    */     //   206: aload 9
/* 817:    */     //   208: invokevirtual 25	java/lang/Throwable:addSuppressed	(Ljava/lang/Throwable;)V
/* 818:    */     //   211: goto +9 -> 220
/* 819:    */     //   214: aload_1
/* 820:    */     //   215: invokeinterface 38 1 0
/* 821:    */     //   220: aload 8
/* 822:    */     //   222: areturn
/* 823:    */     //   223: astore 5
/* 824:    */     //   225: aload 5
/* 825:    */     //   227: astore 4
/* 826:    */     //   229: aload 5
/* 827:    */     //   231: athrow
/* 828:    */     //   232: astore 10
/* 829:    */     //   234: aload_3
/* 830:    */     //   235: ifnull +35 -> 270
/* 831:    */     //   238: aload 4
/* 832:    */     //   240: ifnull +24 -> 264
/* 833:    */     //   243: aload_3
/* 834:    */     //   244: invokeinterface 23 1 0
/* 835:    */     //   249: goto +21 -> 270
/* 836:    */     //   252: astore 11
/* 837:    */     //   254: aload 4
/* 838:    */     //   256: aload 11
/* 839:    */     //   258: invokevirtual 25	java/lang/Throwable:addSuppressed	(Ljava/lang/Throwable;)V
/* 840:    */     //   261: goto +9 -> 270
/* 841:    */     //   264: aload_3
/* 842:    */     //   265: invokeinterface 23 1 0
/* 843:    */     //   270: aload 10
/* 844:    */     //   272: athrow
/* 845:    */     //   273: astore_3
/* 846:    */     //   274: aload_3
/* 847:    */     //   275: astore_2
/* 848:    */     //   276: aload_3
/* 849:    */     //   277: athrow
/* 850:    */     //   278: astore 12
/* 851:    */     //   280: aload_1
/* 852:    */     //   281: ifnull +33 -> 314
/* 853:    */     //   284: aload_2
/* 854:    */     //   285: ifnull +23 -> 308
/* 855:    */     //   288: aload_1
/* 856:    */     //   289: invokeinterface 38 1 0
/* 857:    */     //   294: goto +20 -> 314
/* 858:    */     //   297: astore 13
/* 859:    */     //   299: aload_2
/* 860:    */     //   300: aload 13
/* 861:    */     //   302: invokevirtual 25	java/lang/Throwable:addSuppressed	(Ljava/lang/Throwable;)V
/* 862:    */     //   305: goto +9 -> 314
/* 863:    */     //   308: aload_1
/* 864:    */     //   309: invokeinterface 38 1 0
/* 865:    */     //   314: aload 12
/* 866:    */     //   316: athrow
/* 867:    */     //   317: astore_1
/* 868:    */     //   318: new 27	java/lang/RuntimeException
/* 869:    */     //   321: dup
/* 870:    */     //   322: aload_1
/* 871:    */     //   323: invokevirtual 28	java/sql/SQLException:toString	()Ljava/lang/String;
/* 872:    */     //   326: aload_1
/* 873:    */     //   327: invokespecial 29	java/lang/RuntimeException:<init>	(Ljava/lang/String;Ljava/lang/Throwable;)V
/* 874:    */     //   330: athrow
/* 875:    */     // Line number table:
/* 876:    */     //   Java source line #314	-> byte code offset #0
/* 877:    */     //   Java source line #315	-> byte code offset #6
/* 878:    */     //   Java source line #314	-> byte code offset #15
/* 879:    */     //   Java source line #323	-> byte code offset #18
/* 880:    */     //   Java source line #324	-> byte code offset #21
/* 881:    */     //   Java source line #325	-> byte code offset #36
/* 882:    */     //   Java source line #326	-> byte code offset #44
/* 883:    */     //   Java source line #327	-> byte code offset #51
/* 884:    */     //   Java source line #328	-> byte code offset #61
/* 885:    */     //   Java source line #331	-> byte code offset #74
/* 886:    */     //   Java source line #330	-> byte code offset #147
/* 887:    */     //   Java source line #331	-> byte code offset #150
/* 888:    */     //   Java source line #314	-> byte code offset #223
/* 889:    */     //   Java source line #331	-> byte code offset #232
/* 890:    */     //   Java source line #314	-> byte code offset #273
/* 891:    */     //   Java source line #331	-> byte code offset #278
/* 892:    */     //   Java source line #332	-> byte code offset #317
/* 893:    */     //   Java source line #333	-> byte code offset #318
/* 894:    */     // Local variable table:
/* 895:    */     //   start	length	slot	name	signature
/* 896:    */     //   0	331	0	paramLong	Long
/* 897:    */     //   3	306	1	localConnection	Connection
/* 898:    */     //   317	10	1	localSQLException	SQLException
/* 899:    */     //   5	295	2	localObject1	Object
/* 900:    */     //   14	251	3	localPreparedStatement	PreparedStatement
/* 901:    */     //   273	4	3	localThrowable1	Throwable
/* 902:    */     //   16	239	4	localObject2	Object
/* 903:    */     //   19	7	5	i	int
/* 904:    */     //   223	7	5	localThrowable2	Throwable
/* 905:    */     //   42	3	6	localResultSet	ResultSet
/* 906:    */     //   49	13	7	localList	List
/* 907:    */     //   72	149	8	localAT	AT
/* 908:    */     //   92	5	9	localThrowable3	Throwable
/* 909:    */     //   127	4	9	localThrowable4	Throwable
/* 910:    */     //   168	5	9	localThrowable5	Throwable
/* 911:    */     //   203	4	9	localThrowable6	Throwable
/* 912:    */     //   232	39	10	localObject3	Object
/* 913:    */     //   252	5	11	localThrowable7	Throwable
/* 914:    */     //   278	37	12	localObject4	Object
/* 915:    */     //   297	4	13	localThrowable8	Throwable
/* 916:    */     // Exception table:
/* 917:    */     //   from	to	target	type
/* 918:    */     //   83	89	92	java/lang/Throwable
/* 919:    */     //   118	124	127	java/lang/Throwable
/* 920:    */     //   159	165	168	java/lang/Throwable
/* 921:    */     //   194	200	203	java/lang/Throwable
/* 922:    */     //   18	74	223	java/lang/Throwable
/* 923:    */     //   147	150	223	java/lang/Throwable
/* 924:    */     //   18	74	232	finally
/* 925:    */     //   147	150	232	finally
/* 926:    */     //   223	234	232	finally
/* 927:    */     //   243	249	252	java/lang/Throwable
/* 928:    */     //   6	110	273	java/lang/Throwable
/* 929:    */     //   147	186	273	java/lang/Throwable
/* 930:    */     //   223	273	273	java/lang/Throwable
/* 931:    */     //   6	110	278	finally
/* 932:    */     //   147	186	278	finally
/* 933:    */     //   223	280	278	finally
/* 934:    */     //   288	294	297	java/lang/Throwable
/* 935:    */     //   0	144	317	java/sql/SQLException
/* 936:    */     //   147	220	317	java/sql/SQLException
/* 937:    */     //   223	317	317	java/sql/SQLException
/* 938:    */   }
/* 939:    */   
/* 940:    */   /* Error */
/* 941:    */   public static List<Long> getATsIssuedBy(Long paramLong)
/* 942:    */   {
/* 943:    */     // Byte code:
/* 944:    */     //   0: invokestatic 14	nxt/db/Db:getConnection	()Ljava/sql/Connection;
/* 945:    */     //   3: astore_1
/* 946:    */     //   4: aconst_null
/* 947:    */     //   5: astore_2
/* 948:    */     //   6: aload_1
/* 949:    */     //   7: ldc 39
/* 950:    */     //   9: invokeinterface 16 2 0
/* 951:    */     //   14: astore_3
/* 952:    */     //   15: aconst_null
/* 953:    */     //   16: astore 4
/* 954:    */     //   18: aload_3
/* 955:    */     //   19: iconst_1
/* 956:    */     //   20: aload_0
/* 957:    */     //   21: invokevirtual 32	java/lang/Long:longValue	()J
/* 958:    */     //   24: invokeinterface 33 4 0
/* 959:    */     //   29: aload_3
/* 960:    */     //   30: invokeinterface 17 1 0
/* 961:    */     //   35: astore 5
/* 962:    */     //   37: new 18	java/util/ArrayList
/* 963:    */     //   40: dup
/* 964:    */     //   41: invokespecial 19	java/util/ArrayList:<init>	()V
/* 965:    */     //   44: astore 6
/* 966:    */     //   46: aload 5
/* 967:    */     //   48: invokeinterface 20 1 0
/* 968:    */     //   53: ifeq +25 -> 78
/* 969:    */     //   56: aload 6
/* 970:    */     //   58: aload 5
/* 971:    */     //   60: iconst_1
/* 972:    */     //   61: invokeinterface 40 2 0
/* 973:    */     //   66: invokestatic 9	java/lang/Long:valueOf	(J)Ljava/lang/Long;
/* 974:    */     //   69: invokeinterface 13 2 0
/* 975:    */     //   74: pop
/* 976:    */     //   75: goto -29 -> 46
/* 977:    */     //   78: aload 6
/* 978:    */     //   80: astore 7
/* 979:    */     //   82: aload_3
/* 980:    */     //   83: ifnull +35 -> 118
/* 981:    */     //   86: aload 4
/* 982:    */     //   88: ifnull +24 -> 112
/* 983:    */     //   91: aload_3
/* 984:    */     //   92: invokeinterface 23 1 0
/* 985:    */     //   97: goto +21 -> 118
/* 986:    */     //   100: astore 8
/* 987:    */     //   102: aload 4
/* 988:    */     //   104: aload 8
/* 989:    */     //   106: invokevirtual 25	java/lang/Throwable:addSuppressed	(Ljava/lang/Throwable;)V
/* 990:    */     //   109: goto +9 -> 118
/* 991:    */     //   112: aload_3
/* 992:    */     //   113: invokeinterface 23 1 0
/* 993:    */     //   118: aload_1
/* 994:    */     //   119: ifnull +33 -> 152
/* 995:    */     //   122: aload_2
/* 996:    */     //   123: ifnull +23 -> 146
/* 997:    */     //   126: aload_1
/* 998:    */     //   127: invokeinterface 38 1 0
/* 999:    */     //   132: goto +20 -> 152
/* :00:    */     //   135: astore 8
/* :01:    */     //   137: aload_2
/* :02:    */     //   138: aload 8
/* :03:    */     //   140: invokevirtual 25	java/lang/Throwable:addSuppressed	(Ljava/lang/Throwable;)V
/* :04:    */     //   143: goto +9 -> 152
/* :05:    */     //   146: aload_1
/* :06:    */     //   147: invokeinterface 38 1 0
/* :07:    */     //   152: aload 7
/* :08:    */     //   154: areturn
/* :09:    */     //   155: astore 5
/* :10:    */     //   157: aload 5
/* :11:    */     //   159: astore 4
/* :12:    */     //   161: aload 5
/* :13:    */     //   163: athrow
/* :14:    */     //   164: astore 9
/* :15:    */     //   166: aload_3
/* :16:    */     //   167: ifnull +35 -> 202
/* :17:    */     //   170: aload 4
/* :18:    */     //   172: ifnull +24 -> 196
/* :19:    */     //   175: aload_3
/* :20:    */     //   176: invokeinterface 23 1 0
/* :21:    */     //   181: goto +21 -> 202
/* :22:    */     //   184: astore 10
/* :23:    */     //   186: aload 4
/* :24:    */     //   188: aload 10
/* :25:    */     //   190: invokevirtual 25	java/lang/Throwable:addSuppressed	(Ljava/lang/Throwable;)V
/* :26:    */     //   193: goto +9 -> 202
/* :27:    */     //   196: aload_3
/* :28:    */     //   197: invokeinterface 23 1 0
/* :29:    */     //   202: aload 9
/* :30:    */     //   204: athrow
/* :31:    */     //   205: astore_3
/* :32:    */     //   206: aload_3
/* :33:    */     //   207: astore_2
/* :34:    */     //   208: aload_3
/* :35:    */     //   209: athrow
/* :36:    */     //   210: astore 11
/* :37:    */     //   212: aload_1
/* :38:    */     //   213: ifnull +33 -> 246
/* :39:    */     //   216: aload_2
/* :40:    */     //   217: ifnull +23 -> 240
/* :41:    */     //   220: aload_1
/* :42:    */     //   221: invokeinterface 38 1 0
/* :43:    */     //   226: goto +20 -> 246
/* :44:    */     //   229: astore 12
/* :45:    */     //   231: aload_2
/* :46:    */     //   232: aload 12
/* :47:    */     //   234: invokevirtual 25	java/lang/Throwable:addSuppressed	(Ljava/lang/Throwable;)V
/* :48:    */     //   237: goto +9 -> 246
/* :49:    */     //   240: aload_1
/* :50:    */     //   241: invokeinterface 38 1 0
/* :51:    */     //   246: aload 11
/* :52:    */     //   248: athrow
/* :53:    */     //   249: astore_1
/* :54:    */     //   250: new 27	java/lang/RuntimeException
/* :55:    */     //   253: dup
/* :56:    */     //   254: aload_1
/* :57:    */     //   255: invokevirtual 28	java/sql/SQLException:toString	()Ljava/lang/String;
/* :58:    */     //   258: aload_1
/* :59:    */     //   259: invokespecial 29	java/lang/RuntimeException:<init>	(Ljava/lang/String;Ljava/lang/Throwable;)V
/* :60:    */     //   262: athrow
/* :61:    */     // Line number table:
/* :62:    */     //   Java source line #338	-> byte code offset #0
/* :63:    */     //   Java source line #339	-> byte code offset #6
/* :64:    */     //   Java source line #338	-> byte code offset #15
/* :65:    */     //   Java source line #344	-> byte code offset #18
/* :66:    */     //   Java source line #345	-> byte code offset #29
/* :67:    */     //   Java source line #346	-> byte code offset #37
/* :68:    */     //   Java source line #347	-> byte code offset #46
/* :69:    */     //   Java source line #348	-> byte code offset #56
/* :70:    */     //   Java source line #350	-> byte code offset #78
/* :71:    */     //   Java source line #351	-> byte code offset #82
/* :72:    */     //   Java source line #338	-> byte code offset #155
/* :73:    */     //   Java source line #351	-> byte code offset #164
/* :74:    */     //   Java source line #338	-> byte code offset #205
/* :75:    */     //   Java source line #351	-> byte code offset #210
/* :76:    */     //   Java source line #352	-> byte code offset #249
/* :77:    */     //   Java source line #353	-> byte code offset #250
/* :78:    */     // Local variable table:
/* :79:    */     //   start	length	slot	name	signature
/* :80:    */     //   0	263	0	paramLong	Long
/* :81:    */     //   3	238	1	localConnection	Connection
/* :82:    */     //   249	10	1	localSQLException	SQLException
/* :83:    */     //   5	227	2	localObject1	Object
/* :84:    */     //   14	183	3	localPreparedStatement	PreparedStatement
/* :85:    */     //   205	4	3	localThrowable1	Throwable
/* :86:    */     //   16	171	4	localObject2	Object
/* :87:    */     //   35	24	5	localResultSet	ResultSet
/* :88:    */     //   155	7	5	localThrowable2	Throwable
/* :89:    */     //   44	35	6	localArrayList1	ArrayList
/* :90:    */     //   100	5	8	localThrowable3	Throwable
/* :91:    */     //   135	4	8	localThrowable4	Throwable
/* :92:    */     //   164	39	9	localObject3	Object
/* :93:    */     //   184	5	10	localThrowable5	Throwable
/* :94:    */     //   210	37	11	localObject4	Object
/* :95:    */     //   229	4	12	localThrowable6	Throwable
/* :96:    */     // Exception table:
/* :97:    */     //   from	to	target	type
/* :98:    */     //   91	97	100	java/lang/Throwable
/* :99:    */     //   126	132	135	java/lang/Throwable
/* ;00:    */     //   18	82	155	java/lang/Throwable
/* ;01:    */     //   18	82	164	finally
/* ;02:    */     //   155	166	164	finally
/* ;03:    */     //   175	181	184	java/lang/Throwable
/* ;04:    */     //   6	118	205	java/lang/Throwable
/* ;05:    */     //   155	205	205	java/lang/Throwable
/* ;06:    */     //   6	118	210	finally
/* ;07:    */     //   155	212	210	finally
/* ;08:    */     //   220	226	229	java/lang/Throwable
/* ;09:    */     //   0	152	249	java/sql/SQLException
/* ;10:    */     //   155	249	249	java/sql/SQLException
/* ;11:    */   }
/* ;12:    */   
/* ;13:    */   /* Error */
/* ;14:    */   static boolean isATAccountId(Long paramLong)
/* ;15:    */   {
/* ;16:    */     // Byte code:
/* ;17:    */     //   0: invokestatic 14	nxt/db/Db:getConnection	()Ljava/sql/Connection;
/* ;18:    */     //   3: astore_1
/* ;19:    */     //   4: aconst_null
/* ;20:    */     //   5: astore_2
/* ;21:    */     //   6: aload_1
/* ;22:    */     //   7: ldc 106
/* ;23:    */     //   9: invokeinterface 16 2 0
/* ;24:    */     //   14: astore_3
/* ;25:    */     //   15: aconst_null
/* ;26:    */     //   16: astore 4
/* ;27:    */     //   18: aload_3
/* ;28:    */     //   19: iconst_1
/* ;29:    */     //   20: aload_0
/* ;30:    */     //   21: invokevirtual 32	java/lang/Long:longValue	()J
/* ;31:    */     //   24: invokeinterface 33 4 0
/* ;32:    */     //   29: aload_3
/* ;33:    */     //   30: invokeinterface 17 1 0
/* ;34:    */     //   35: astore 5
/* ;35:    */     //   37: aload 5
/* ;36:    */     //   39: invokeinterface 20 1 0
/* ;37:    */     //   44: istore 6
/* ;38:    */     //   46: aload_3
/* ;39:    */     //   47: ifnull +35 -> 82
/* ;40:    */     //   50: aload 4
/* ;41:    */     //   52: ifnull +24 -> 76
/* ;42:    */     //   55: aload_3
/* ;43:    */     //   56: invokeinterface 23 1 0
/* ;44:    */     //   61: goto +21 -> 82
/* ;45:    */     //   64: astore 7
/* ;46:    */     //   66: aload 4
/* ;47:    */     //   68: aload 7
/* ;48:    */     //   70: invokevirtual 25	java/lang/Throwable:addSuppressed	(Ljava/lang/Throwable;)V
/* ;49:    */     //   73: goto +9 -> 82
/* ;50:    */     //   76: aload_3
/* ;51:    */     //   77: invokeinterface 23 1 0
/* ;52:    */     //   82: aload_1
/* ;53:    */     //   83: ifnull +33 -> 116
/* ;54:    */     //   86: aload_2
/* ;55:    */     //   87: ifnull +23 -> 110
/* ;56:    */     //   90: aload_1
/* ;57:    */     //   91: invokeinterface 38 1 0
/* ;58:    */     //   96: goto +20 -> 116
/* ;59:    */     //   99: astore 7
/* ;60:    */     //   101: aload_2
/* ;61:    */     //   102: aload 7
/* ;62:    */     //   104: invokevirtual 25	java/lang/Throwable:addSuppressed	(Ljava/lang/Throwable;)V
/* ;63:    */     //   107: goto +9 -> 116
/* ;64:    */     //   110: aload_1
/* ;65:    */     //   111: invokeinterface 38 1 0
/* ;66:    */     //   116: iload 6
/* ;67:    */     //   118: ireturn
/* ;68:    */     //   119: astore 5
/* ;69:    */     //   121: aload 5
/* ;70:    */     //   123: astore 4
/* ;71:    */     //   125: aload 5
/* ;72:    */     //   127: athrow
/* ;73:    */     //   128: astore 8
/* ;74:    */     //   130: aload_3
/* ;75:    */     //   131: ifnull +35 -> 166
/* ;76:    */     //   134: aload 4
/* ;77:    */     //   136: ifnull +24 -> 160
/* ;78:    */     //   139: aload_3
/* ;79:    */     //   140: invokeinterface 23 1 0
/* ;80:    */     //   145: goto +21 -> 166
/* ;81:    */     //   148: astore 9
/* ;82:    */     //   150: aload 4
/* ;83:    */     //   152: aload 9
/* ;84:    */     //   154: invokevirtual 25	java/lang/Throwable:addSuppressed	(Ljava/lang/Throwable;)V
/* ;85:    */     //   157: goto +9 -> 166
/* ;86:    */     //   160: aload_3
/* ;87:    */     //   161: invokeinterface 23 1 0
/* ;88:    */     //   166: aload 8
/* ;89:    */     //   168: athrow
/* ;90:    */     //   169: astore_3
/* ;91:    */     //   170: aload_3
/* ;92:    */     //   171: astore_2
/* ;93:    */     //   172: aload_3
/* ;94:    */     //   173: athrow
/* ;95:    */     //   174: astore 10
/* ;96:    */     //   176: aload_1
/* ;97:    */     //   177: ifnull +33 -> 210
/* ;98:    */     //   180: aload_2
/* ;99:    */     //   181: ifnull +23 -> 204
/* <00:    */     //   184: aload_1
/* <01:    */     //   185: invokeinterface 38 1 0
/* <02:    */     //   190: goto +20 -> 210
/* <03:    */     //   193: astore 11
/* <04:    */     //   195: aload_2
/* <05:    */     //   196: aload 11
/* <06:    */     //   198: invokevirtual 25	java/lang/Throwable:addSuppressed	(Ljava/lang/Throwable;)V
/* <07:    */     //   201: goto +9 -> 210
/* <08:    */     //   204: aload_1
/* <09:    */     //   205: invokeinterface 38 1 0
/* <10:    */     //   210: aload 10
/* <11:    */     //   212: athrow
/* <12:    */     //   213: astore_1
/* <13:    */     //   214: new 27	java/lang/RuntimeException
/* <14:    */     //   217: dup
/* <15:    */     //   218: aload_1
/* <16:    */     //   219: invokevirtual 28	java/sql/SQLException:toString	()Ljava/lang/String;
/* <17:    */     //   222: aload_1
/* <18:    */     //   223: invokespecial 29	java/lang/RuntimeException:<init>	(Ljava/lang/String;Ljava/lang/Throwable;)V
/* <19:    */     //   226: athrow
/* <20:    */     // Line number table:
/* <21:    */     //   Java source line #514	-> byte code offset #0
/* <22:    */     //   Java source line #515	-> byte code offset #6
/* <23:    */     //   Java source line #514	-> byte code offset #15
/* <24:    */     //   Java source line #517	-> byte code offset #18
/* <25:    */     //   Java source line #518	-> byte code offset #29
/* <26:    */     //   Java source line #519	-> byte code offset #37
/* <27:    */     //   Java source line #520	-> byte code offset #46
/* <28:    */     //   Java source line #514	-> byte code offset #119
/* <29:    */     //   Java source line #520	-> byte code offset #128
/* <30:    */     //   Java source line #514	-> byte code offset #169
/* <31:    */     //   Java source line #520	-> byte code offset #174
/* <32:    */     //   Java source line #521	-> byte code offset #213
/* <33:    */     //   Java source line #522	-> byte code offset #214
/* <34:    */     // Local variable table:
/* <35:    */     //   start	length	slot	name	signature
/* <36:    */     //   0	227	0	paramLong	Long
/* <37:    */     //   3	202	1	localConnection	Connection
/* <38:    */     //   213	10	1	localSQLException	SQLException
/* <39:    */     //   5	191	2	localObject1	Object
/* <40:    */     //   14	147	3	localPreparedStatement	PreparedStatement
/* <41:    */     //   169	4	3	localThrowable1	Throwable
/* <42:    */     //   16	135	4	localObject2	Object
/* <43:    */     //   35	3	5	localResultSet	ResultSet
/* <44:    */     //   119	7	5	localThrowable2	Throwable
/* <45:    */     //   64	5	7	localThrowable3	Throwable
/* <46:    */     //   99	4	7	localThrowable4	Throwable
/* <47:    */     //   128	39	8	localObject3	Object
/* <48:    */     //   148	5	9	localThrowable5	Throwable
/* <49:    */     //   174	37	10	localObject4	Object
/* <50:    */     //   193	4	11	localThrowable6	Throwable
/* <51:    */     // Exception table:
/* <52:    */     //   from	to	target	type
/* <53:    */     //   55	61	64	java/lang/Throwable
/* <54:    */     //   90	96	99	java/lang/Throwable
/* <55:    */     //   18	46	119	java/lang/Throwable
/* <56:    */     //   18	46	128	finally
/* <57:    */     //   119	130	128	finally
/* <58:    */     //   139	145	148	java/lang/Throwable
/* <59:    */     //   6	82	169	java/lang/Throwable
/* <60:    */     //   119	169	169	java/lang/Throwable
/* <61:    */     //   6	82	174	finally
/* <62:    */     //   119	176	174	finally
/* <63:    */     //   184	190	193	java/lang/Throwable
/* <64:    */     //   0	116	213	java/sql/SQLException
/* <65:    */     //   119	213	213	java/sql/SQLException
/* <66:    */   }
/* <67:    */   
/* <68:    */   /* Error */
/* <69:    */   private static byte[] compressState(byte[] paramArrayOfByte)
/* <70:    */   {
/* <71:    */     // Byte code:
/* <72:    */     //   0: aload_0
/* <73:    */     //   1: ifnull +8 -> 9
/* <74:    */     //   4: aload_0
/* <75:    */     //   5: arraylength
/* <76:    */     //   6: ifne +5 -> 11
/* <77:    */     //   9: aconst_null
/* <78:    */     //   10: areturn
/* <79:    */     //   11: new 107	java/io/ByteArrayOutputStream
/* <80:    */     //   14: dup
/* <81:    */     //   15: invokespecial 108	java/io/ByteArrayOutputStream:<init>	()V
/* <82:    */     //   18: astore_1
/* <83:    */     //   19: aconst_null
/* <84:    */     //   20: astore_2
/* <85:    */     //   21: new 109	java/util/zip/GZIPOutputStream
/* <86:    */     //   24: dup
/* <87:    */     //   25: aload_1
/* <88:    */     //   26: invokespecial 110	java/util/zip/GZIPOutputStream:<init>	(Ljava/io/OutputStream;)V
/* <89:    */     //   29: astore_3
/* <90:    */     //   30: aconst_null
/* <91:    */     //   31: astore 4
/* <92:    */     //   33: aload_3
/* <93:    */     //   34: aload_0
/* <94:    */     //   35: invokevirtual 111	java/util/zip/GZIPOutputStream:write	([B)V
/* <95:    */     //   38: aload_3
/* <96:    */     //   39: invokevirtual 112	java/util/zip/GZIPOutputStream:flush	()V
/* <97:    */     //   42: aload_3
/* <98:    */     //   43: invokevirtual 113	java/util/zip/GZIPOutputStream:close	()V
/* <99:    */     //   46: aload_1
/* =00:    */     //   47: invokevirtual 114	java/io/ByteArrayOutputStream:toByteArray	()[B
/* =01:    */     //   50: astore 5
/* =02:    */     //   52: aload_3
/* =03:    */     //   53: ifnull +31 -> 84
/* =04:    */     //   56: aload 4
/* =05:    */     //   58: ifnull +22 -> 80
/* =06:    */     //   61: aload_3
/* =07:    */     //   62: invokevirtual 113	java/util/zip/GZIPOutputStream:close	()V
/* =08:    */     //   65: goto +19 -> 84
/* =09:    */     //   68: astore 6
/* =10:    */     //   70: aload 4
/* =11:    */     //   72: aload 6
/* =12:    */     //   74: invokevirtual 25	java/lang/Throwable:addSuppressed	(Ljava/lang/Throwable;)V
/* =13:    */     //   77: goto +7 -> 84
/* =14:    */     //   80: aload_3
/* =15:    */     //   81: invokevirtual 113	java/util/zip/GZIPOutputStream:close	()V
/* =16:    */     //   84: aload_1
/* =17:    */     //   85: ifnull +29 -> 114
/* =18:    */     //   88: aload_2
/* =19:    */     //   89: ifnull +21 -> 110
/* =20:    */     //   92: aload_1
/* =21:    */     //   93: invokevirtual 115	java/io/ByteArrayOutputStream:close	()V
/* =22:    */     //   96: goto +18 -> 114
/* =23:    */     //   99: astore 6
/* =24:    */     //   101: aload_2
/* =25:    */     //   102: aload 6
/* =26:    */     //   104: invokevirtual 25	java/lang/Throwable:addSuppressed	(Ljava/lang/Throwable;)V
/* =27:    */     //   107: goto +7 -> 114
/* =28:    */     //   110: aload_1
/* =29:    */     //   111: invokevirtual 115	java/io/ByteArrayOutputStream:close	()V
/* =30:    */     //   114: aload 5
/* =31:    */     //   116: areturn
/* =32:    */     //   117: astore 5
/* =33:    */     //   119: aload 5
/* =34:    */     //   121: astore 4
/* =35:    */     //   123: aload 5
/* =36:    */     //   125: athrow
/* =37:    */     //   126: astore 7
/* =38:    */     //   128: aload_3
/* =39:    */     //   129: ifnull +31 -> 160
/* =40:    */     //   132: aload 4
/* =41:    */     //   134: ifnull +22 -> 156
/* =42:    */     //   137: aload_3
/* =43:    */     //   138: invokevirtual 113	java/util/zip/GZIPOutputStream:close	()V
/* =44:    */     //   141: goto +19 -> 160
/* =45:    */     //   144: astore 8
/* =46:    */     //   146: aload 4
/* =47:    */     //   148: aload 8
/* =48:    */     //   150: invokevirtual 25	java/lang/Throwable:addSuppressed	(Ljava/lang/Throwable;)V
/* =49:    */     //   153: goto +7 -> 160
/* =50:    */     //   156: aload_3
/* =51:    */     //   157: invokevirtual 113	java/util/zip/GZIPOutputStream:close	()V
/* =52:    */     //   160: aload 7
/* =53:    */     //   162: athrow
/* =54:    */     //   163: astore_3
/* =55:    */     //   164: aload_3
/* =56:    */     //   165: astore_2
/* =57:    */     //   166: aload_3
/* =58:    */     //   167: athrow
/* =59:    */     //   168: astore 9
/* =60:    */     //   170: aload_1
/* =61:    */     //   171: ifnull +29 -> 200
/* =62:    */     //   174: aload_2
/* =63:    */     //   175: ifnull +21 -> 196
/* =64:    */     //   178: aload_1
/* =65:    */     //   179: invokevirtual 115	java/io/ByteArrayOutputStream:close	()V
/* =66:    */     //   182: goto +18 -> 200
/* =67:    */     //   185: astore 10
/* =68:    */     //   187: aload_2
/* =69:    */     //   188: aload 10
/* =70:    */     //   190: invokevirtual 25	java/lang/Throwable:addSuppressed	(Ljava/lang/Throwable;)V
/* =71:    */     //   193: goto +7 -> 200
/* =72:    */     //   196: aload_1
/* =73:    */     //   197: invokevirtual 115	java/io/ByteArrayOutputStream:close	()V
/* =74:    */     //   200: aload 9
/* =75:    */     //   202: athrow
/* =76:    */     //   203: astore_1
/* =77:    */     //   204: new 27	java/lang/RuntimeException
/* =78:    */     //   207: dup
/* =79:    */     //   208: aload_1
/* =80:    */     //   209: invokevirtual 117	java/io/IOException:getMessage	()Ljava/lang/String;
/* =81:    */     //   212: aload_1
/* =82:    */     //   213: invokespecial 29	java/lang/RuntimeException:<init>	(Ljava/lang/String;Ljava/lang/Throwable;)V
/* =83:    */     //   216: athrow
/* =84:    */     // Line number table:
/* =85:    */     //   Java source line #527	-> byte code offset #0
/* =86:    */     //   Java source line #528	-> byte code offset #9
/* =87:    */     //   Java source line #531	-> byte code offset #11
/* =88:    */     //   Java source line #532	-> byte code offset #21
/* =89:    */     //   Java source line #531	-> byte code offset #30
/* =90:    */     //   Java source line #533	-> byte code offset #33
/* =91:    */     //   Java source line #534	-> byte code offset #38
/* =92:    */     //   Java source line #535	-> byte code offset #42
/* =93:    */     //   Java source line #536	-> byte code offset #46
/* =94:    */     //   Java source line #537	-> byte code offset #52
/* =95:    */     //   Java source line #531	-> byte code offset #117
/* =96:    */     //   Java source line #537	-> byte code offset #126
/* =97:    */     //   Java source line #531	-> byte code offset #163
/* =98:    */     //   Java source line #537	-> byte code offset #168
/* =99:    */     //   Java source line #538	-> byte code offset #204
/* >00:    */     // Local variable table:
/* >01:    */     //   start	length	slot	name	signature
/* >02:    */     //   0	217	0	paramArrayOfByte	byte[]
/* >03:    */     //   18	179	1	localByteArrayOutputStream	java.io.ByteArrayOutputStream
/* >04:    */     //   203	10	1	localIOException	java.io.IOException
/* >05:    */     //   20	168	2	localObject1	Object
/* >06:    */     //   29	128	3	localGZIPOutputStream	java.util.zip.GZIPOutputStream
/* >07:    */     //   163	4	3	localThrowable1	Throwable
/* >08:    */     //   31	116	4	localObject2	Object
/* >09:    */     //   117	7	5	localThrowable2	Throwable
/* >10:    */     //   68	5	6	localThrowable3	Throwable
/* >11:    */     //   99	4	6	localThrowable4	Throwable
/* >12:    */     //   126	35	7	localObject3	Object
/* >13:    */     //   144	5	8	localThrowable5	Throwable
/* >14:    */     //   168	33	9	localObject4	Object
/* >15:    */     //   185	4	10	localThrowable6	Throwable
/* >16:    */     // Exception table:
/* >17:    */     //   from	to	target	type
/* >18:    */     //   61	65	68	java/lang/Throwable
/* >19:    */     //   92	96	99	java/lang/Throwable
/* >20:    */     //   33	52	117	java/lang/Throwable
/* >21:    */     //   33	52	126	finally
/* >22:    */     //   117	128	126	finally
/* >23:    */     //   137	141	144	java/lang/Throwable
/* >24:    */     //   21	84	163	java/lang/Throwable
/* >25:    */     //   117	163	163	java/lang/Throwable
/* >26:    */     //   21	84	168	finally
/* >27:    */     //   117	170	168	finally
/* >28:    */     //   178	182	185	java/lang/Throwable
/* >29:    */     //   11	114	203	java/io/IOException
/* >30:    */     //   117	203	203	java/io/IOException
/* >31:    */   }
/* >32:    */   
/* >33:    */   /* Error */
/* >34:    */   private static byte[] decompressState(byte[] paramArrayOfByte)
/* >35:    */   {
/* >36:    */     // Byte code:
/* >37:    */     //   0: aload_0
/* >38:    */     //   1: ifnull +8 -> 9
/* >39:    */     //   4: aload_0
/* >40:    */     //   5: arraylength
/* >41:    */     //   6: ifne +5 -> 11
/* >42:    */     //   9: aconst_null
/* >43:    */     //   10: areturn
/* >44:    */     //   11: new 118	java/io/ByteArrayInputStream
/* >45:    */     //   14: dup
/* >46:    */     //   15: aload_0
/* >47:    */     //   16: invokespecial 119	java/io/ByteArrayInputStream:<init>	([B)V
/* >48:    */     //   19: astore_1
/* >49:    */     //   20: aconst_null
/* >50:    */     //   21: astore_2
/* >51:    */     //   22: new 120	java/util/zip/GZIPInputStream
/* >52:    */     //   25: dup
/* >53:    */     //   26: aload_1
/* >54:    */     //   27: invokespecial 121	java/util/zip/GZIPInputStream:<init>	(Ljava/io/InputStream;)V
/* >55:    */     //   30: astore_3
/* >56:    */     //   31: aconst_null
/* >57:    */     //   32: astore 4
/* >58:    */     //   34: new 107	java/io/ByteArrayOutputStream
/* >59:    */     //   37: dup
/* >60:    */     //   38: invokespecial 108	java/io/ByteArrayOutputStream:<init>	()V
/* >61:    */     //   41: astore 5
/* >62:    */     //   43: aconst_null
/* >63:    */     //   44: astore 6
/* >64:    */     //   46: sipush 256
/* >65:    */     //   49: newarray 
/* >66:    */     //   52: iconst_4
/* >67:    */     //   53: aload_3
/* >68:    */     //   54: aload 7
/* >69:    */     //   56: iconst_0
/* >70:    */     //   57: aload 7
/* >71:    */     //   59: arraylength
/* >72:    */     //   60: invokevirtual 122	java/util/zip/GZIPInputStream:read	([BII)I
/* >73:    */     //   63: dup
/* >74:    */     //   64: istore 8
/* >75:    */     //   66: ifle +16 -> 82
/* >76:    */     //   69: aload 5
/* >77:    */     //   71: aload 7
/* >78:    */     //   73: iconst_0
/* >79:    */     //   74: iload 8
/* >80:    */     //   76: invokevirtual 123	java/io/ByteArrayOutputStream:write	([BII)V
/* >81:    */     //   79: goto -26 -> 53
/* >82:    */     //   82: aload 5
/* >83:    */     //   84: invokevirtual 124	java/io/ByteArrayOutputStream:flush	()V
/* >84:    */     //   87: aload 5
/* >85:    */     //   89: invokevirtual 114	java/io/ByteArrayOutputStream:toByteArray	()[B
/* >86:    */     //   92: astore 9
/* >87:    */     //   94: aload 5
/* >88:    */     //   96: ifnull +33 -> 129
/* >89:    */     //   99: aload 6
/* >90:    */     //   101: ifnull +23 -> 124
/* >91:    */     //   104: aload 5
/* >92:    */     //   106: invokevirtual 115	java/io/ByteArrayOutputStream:close	()V
/* >93:    */     //   109: goto +20 -> 129
/* >94:    */     //   112: astore 10
/* >95:    */     //   114: aload 6
/* >96:    */     //   116: aload 10
/* >97:    */     //   118: invokevirtual 25	java/lang/Throwable:addSuppressed	(Ljava/lang/Throwable;)V
/* >98:    */     //   121: goto +8 -> 129
/* >99:    */     //   124: aload 5
/* ?00:    */     //   126: invokevirtual 115	java/io/ByteArrayOutputStream:close	()V
/* ?01:    */     //   129: aload_3
/* ?02:    */     //   130: ifnull +31 -> 161
/* ?03:    */     //   133: aload 4
/* ?04:    */     //   135: ifnull +22 -> 157
/* ?05:    */     //   138: aload_3
/* ?06:    */     //   139: invokevirtual 125	java/util/zip/GZIPInputStream:close	()V
/* ?07:    */     //   142: goto +19 -> 161
/* ?08:    */     //   145: astore 10
/* ?09:    */     //   147: aload 4
/* ?10:    */     //   149: aload 10
/* ?11:    */     //   151: invokevirtual 25	java/lang/Throwable:addSuppressed	(Ljava/lang/Throwable;)V
/* ?12:    */     //   154: goto +7 -> 161
/* ?13:    */     //   157: aload_3
/* ?14:    */     //   158: invokevirtual 125	java/util/zip/GZIPInputStream:close	()V
/* ?15:    */     //   161: aload_1
/* ?16:    */     //   162: ifnull +29 -> 191
/* ?17:    */     //   165: aload_2
/* ?18:    */     //   166: ifnull +21 -> 187
/* ?19:    */     //   169: aload_1
/* ?20:    */     //   170: invokevirtual 126	java/io/ByteArrayInputStream:close	()V
/* ?21:    */     //   173: goto +18 -> 191
/* ?22:    */     //   176: astore 10
/* ?23:    */     //   178: aload_2
/* ?24:    */     //   179: aload 10
/* ?25:    */     //   181: invokevirtual 25	java/lang/Throwable:addSuppressed	(Ljava/lang/Throwable;)V
/* ?26:    */     //   184: goto +7 -> 191
/* ?27:    */     //   187: aload_1
/* ?28:    */     //   188: invokevirtual 126	java/io/ByteArrayInputStream:close	()V
/* ?29:    */     //   191: aload 9
/* ?30:    */     //   193: areturn
/* ?31:    */     //   194: astore 7
/* ?32:    */     //   196: aload 7
/* ?33:    */     //   198: astore 6
/* ?34:    */     //   200: aload 7
/* ?35:    */     //   202: athrow
/* ?36:    */     //   203: astore 11
/* ?37:    */     //   205: aload 5
/* ?38:    */     //   207: ifnull +33 -> 240
/* ?39:    */     //   210: aload 6
/* ?40:    */     //   212: ifnull +23 -> 235
/* ?41:    */     //   215: aload 5
/* ?42:    */     //   217: invokevirtual 115	java/io/ByteArrayOutputStream:close	()V
/* ?43:    */     //   220: goto +20 -> 240
/* ?44:    */     //   223: astore 12
/* ?45:    */     //   225: aload 6
/* ?46:    */     //   227: aload 12
/* ?47:    */     //   229: invokevirtual 25	java/lang/Throwable:addSuppressed	(Ljava/lang/Throwable;)V
/* ?48:    */     //   232: goto +8 -> 240
/* ?49:    */     //   235: aload 5
/* ?50:    */     //   237: invokevirtual 115	java/io/ByteArrayOutputStream:close	()V
/* ?51:    */     //   240: aload 11
/* ?52:    */     //   242: athrow
/* ?53:    */     //   243: astore 5
/* ?54:    */     //   245: aload 5
/* ?55:    */     //   247: astore 4
/* ?56:    */     //   249: aload 5
/* ?57:    */     //   251: athrow
/* ?58:    */     //   252: astore 13
/* ?59:    */     //   254: aload_3
/* ?60:    */     //   255: ifnull +31 -> 286
/* ?61:    */     //   258: aload 4
/* ?62:    */     //   260: ifnull +22 -> 282
/* ?63:    */     //   263: aload_3
/* ?64:    */     //   264: invokevirtual 125	java/util/zip/GZIPInputStream:close	()V
/* ?65:    */     //   267: goto +19 -> 286
/* ?66:    */     //   270: astore 14
/* ?67:    */     //   272: aload 4
/* ?68:    */     //   274: aload 14
/* ?69:    */     //   276: invokevirtual 25	java/lang/Throwable:addSuppressed	(Ljava/lang/Throwable;)V
/* ?70:    */     //   279: goto +7 -> 286
/* ?71:    */     //   282: aload_3
/* ?72:    */     //   283: invokevirtual 125	java/util/zip/GZIPInputStream:close	()V
/* ?73:    */     //   286: aload 13
/* ?74:    */     //   288: athrow
/* ?75:    */     //   289: astore_3
/* ?76:    */     //   290: aload_3
/* ?77:    */     //   291: astore_2
/* ?78:    */     //   292: aload_3
/* ?79:    */     //   293: athrow
/* ?80:    */     //   294: astore 15
/* ?81:    */     //   296: aload_1
/* ?82:    */     //   297: ifnull +29 -> 326
/* ?83:    */     //   300: aload_2
/* ?84:    */     //   301: ifnull +21 -> 322
/* ?85:    */     //   304: aload_1
/* ?86:    */     //   305: invokevirtual 126	java/io/ByteArrayInputStream:close	()V
/* ?87:    */     //   308: goto +18 -> 326
/* ?88:    */     //   311: astore 16
/* ?89:    */     //   313: aload_2
/* ?90:    */     //   314: aload 16
/* ?91:    */     //   316: invokevirtual 25	java/lang/Throwable:addSuppressed	(Ljava/lang/Throwable;)V
/* ?92:    */     //   319: goto +7 -> 326
/* ?93:    */     //   322: aload_1
/* ?94:    */     //   323: invokevirtual 126	java/io/ByteArrayInputStream:close	()V
/* ?95:    */     //   326: aload 15
/* ?96:    */     //   328: athrow
/* ?97:    */     //   329: astore_1
/* ?98:    */     //   330: new 27	java/lang/RuntimeException
/* ?99:    */     //   333: dup
/* @00:    */     //   334: aload_1
/* @01:    */     //   335: invokevirtual 117	java/io/IOException:getMessage	()Ljava/lang/String;
/* @02:    */     //   338: aload_1
/* @03:    */     //   339: invokespecial 29	java/lang/RuntimeException:<init>	(Ljava/lang/String;Ljava/lang/Throwable;)V
/* @04:    */     //   342: athrow
/* @05:    */     // Line number table:
/* @06:    */     //   Java source line #543	-> byte code offset #0
/* @07:    */     //   Java source line #544	-> byte code offset #9
/* @08:    */     //   Java source line #547	-> byte code offset #11
/* @09:    */     //   Java source line #548	-> byte code offset #22
/* @10:    */     //   Java source line #547	-> byte code offset #31
/* @11:    */     //   Java source line #549	-> byte code offset #34
/* @12:    */     //   Java source line #547	-> byte code offset #43
/* @13:    */     //   Java source line #550	-> byte code offset #46
/* @14:    */     //   Java source line #552	-> byte code offset #53
/* @15:    */     //   Java source line #553	-> byte code offset #69
/* @16:    */     //   Java source line #555	-> byte code offset #82
/* @17:    */     //   Java source line #556	-> byte code offset #87
/* @18:    */     //   Java source line #557	-> byte code offset #94
/* @19:    */     //   Java source line #547	-> byte code offset #194
/* @20:    */     //   Java source line #557	-> byte code offset #203
/* @21:    */     //   Java source line #547	-> byte code offset #243
/* @22:    */     //   Java source line #557	-> byte code offset #252
/* @23:    */     //   Java source line #547	-> byte code offset #289
/* @24:    */     //   Java source line #557	-> byte code offset #294
/* @25:    */     //   Java source line #558	-> byte code offset #330
/* @26:    */     // Local variable table:
/* @27:    */     //   start	length	slot	name	signature
/* @28:    */     //   0	343	0	paramArrayOfByte	byte[]
/* @29:    */     //   19	304	1	localByteArrayInputStream	java.io.ByteArrayInputStream
/* @30:    */     //   329	10	1	localIOException	java.io.IOException
/* @31:    */     //   21	293	2	localObject1	Object
/* @32:    */     //   30	253	3	localGZIPInputStream	java.util.zip.GZIPInputStream
/* @33:    */     //   289	4	3	localThrowable1	Throwable
/* @34:    */     //   32	241	4	localObject2	Object
/* @35:    */     //   41	195	5	localByteArrayOutputStream	java.io.ByteArrayOutputStream
/* @36:    */     //   243	7	5	localThrowable2	Throwable
/* @37:    */     //   44	182	6	localObject3	Object
/* @38:    */     //   51	21	7	arrayOfByte1	byte[]
/* @39:    */     //   194	7	7	localThrowable3	Throwable
/* @40:    */     //   64	11	8	i	int
/* @41:    */     //   92	100	9	arrayOfByte2	byte[]
/* @42:    */     //   112	5	10	localThrowable4	Throwable
/* @43:    */     //   145	5	10	localThrowable5	Throwable
/* @44:    */     //   176	4	10	localThrowable6	Throwable
/* @45:    */     //   203	38	11	localObject4	Object
/* @46:    */     //   223	5	12	localThrowable7	Throwable
/* @47:    */     //   252	35	13	localObject5	Object
/* @48:    */     //   270	5	14	localThrowable8	Throwable
/* @49:    */     //   294	33	15	localObject6	Object
/* @50:    */     //   311	4	16	localThrowable9	Throwable
/* @51:    */     // Exception table:
/* @52:    */     //   from	to	target	type
/* @53:    */     //   104	109	112	java/lang/Throwable
/* @54:    */     //   138	142	145	java/lang/Throwable
/* @55:    */     //   169	173	176	java/lang/Throwable
/* @56:    */     //   46	94	194	java/lang/Throwable
/* @57:    */     //   46	94	203	finally
/* @58:    */     //   194	205	203	finally
/* @59:    */     //   215	220	223	java/lang/Throwable
/* @60:    */     //   34	129	243	java/lang/Throwable
/* @61:    */     //   194	243	243	java/lang/Throwable
/* @62:    */     //   34	129	252	finally
/* @63:    */     //   194	254	252	finally
/* @64:    */     //   263	267	270	java/lang/Throwable
/* @65:    */     //   22	161	289	java/lang/Throwable
/* @66:    */     //   194	289	289	java/lang/Throwable
/* @67:    */     //   22	161	294	finally
/* @68:    */     //   194	296	294	finally
/* @69:    */     //   304	308	311	java/lang/Throwable
/* @70:    */     //   11	191	329	java/io/IOException
/* @71:    */     //   194	329	329	java/io/IOException
/* @72:    */   }
/* @73:    */   
/* @74:    */   static void init() {}
/* @75:    */ }


/* Location:           E:\java decompi;er\burst.jar
 * Qualified Name:     nxt.AT
 * JD-Core Version:    0.7.1
 */