/*  1:   */ package nxt.http;
/*  2:   */ 
/*  3:   */ public final class BroadcastTransaction
/*  4:   */   extends APIServlet.APIRequestHandler
/*  5:   */ {
/*  6:15 */   static final BroadcastTransaction instance = new BroadcastTransaction();
/*  7:   */   
/*  8:   */   private BroadcastTransaction()
/*  9:   */   {
/* 10:18 */     super(new APITag[] { APITag.TRANSACTIONS }, new String[] { "transactionBytes", "transactionJSON" });
/* 11:   */   }
/* 12:   */   
/* 13:   */   /* Error */
/* 14:   */   org.json.simple.JSONStreamAware processRequest(javax.servlet.http.HttpServletRequest paramHttpServletRequest)
/* 15:   */     throws nxt.NxtException
/* 16:   */   {
/* 17:   */     // Byte code:
/* 18:   */     //   0: aload_1
/* 19:   */     //   1: ldc 4
/* 20:   */     //   3: invokeinterface 7 2 0
/* 21:   */     //   8: invokestatic 8	nxt/util/Convert:emptyToNull	(Ljava/lang/String;)Ljava/lang/String;
/* 22:   */     //   11: astore_2
/* 23:   */     //   12: aload_1
/* 24:   */     //   13: ldc 5
/* 25:   */     //   15: invokeinterface 7 2 0
/* 26:   */     //   20: invokestatic 8	nxt/util/Convert:emptyToNull	(Ljava/lang/String;)Ljava/lang/String;
/* 27:   */     //   23: astore_3
/* 28:   */     //   24: aload_2
/* 29:   */     //   25: aload_3
/* 30:   */     //   26: invokestatic 9	nxt/http/ParameterParser:parseTransaction	(Ljava/lang/String;Ljava/lang/String;)Lnxt/Transaction;
/* 31:   */     //   29: astore 4
/* 32:   */     //   31: new 10	org/json/simple/JSONObject
/* 33:   */     //   34: dup
/* 34:   */     //   35: invokespecial 11	org/json/simple/JSONObject:<init>	()V
/* 35:   */     //   38: astore 5
/* 36:   */     //   40: aload 4
/* 37:   */     //   42: invokeinterface 12 1 0
/* 38:   */     //   47: invokestatic 13	nxt/Nxt:getTransactionProcessor	()Lnxt/TransactionProcessor;
/* 39:   */     //   50: aload 4
/* 40:   */     //   52: invokeinterface 14 2 0
/* 41:   */     //   57: aload 5
/* 42:   */     //   59: ldc 15
/* 43:   */     //   61: aload 4
/* 44:   */     //   63: invokeinterface 16 1 0
/* 45:   */     //   68: invokevirtual 17	org/json/simple/JSONObject:put	(Ljava/lang/Object;Ljava/lang/Object;)Ljava/lang/Object;
/* 46:   */     //   71: pop
/* 47:   */     //   72: aload 5
/* 48:   */     //   74: ldc 18
/* 49:   */     //   76: aload 4
/* 50:   */     //   78: invokeinterface 19 1 0
/* 51:   */     //   83: invokevirtual 17	org/json/simple/JSONObject:put	(Ljava/lang/Object;Ljava/lang/Object;)Ljava/lang/Object;
/* 52:   */     //   86: pop
/* 53:   */     //   87: goto +71 -> 158
/* 54:   */     //   90: astore 6
/* 55:   */     //   92: aload 6
/* 56:   */     //   94: invokevirtual 22	java/lang/Exception:getMessage	()Ljava/lang/String;
/* 57:   */     //   97: aload 6
/* 58:   */     //   99: invokestatic 23	nxt/util/Logger:logDebugMessage	(Ljava/lang/String;Ljava/lang/Exception;)V
/* 59:   */     //   102: aload 5
/* 60:   */     //   104: ldc 24
/* 61:   */     //   106: iconst_4
/* 62:   */     //   107: invokestatic 25	java/lang/Integer:valueOf	(I)Ljava/lang/Integer;
/* 63:   */     //   110: invokevirtual 17	org/json/simple/JSONObject:put	(Ljava/lang/Object;Ljava/lang/Object;)Ljava/lang/Object;
/* 64:   */     //   113: pop
/* 65:   */     //   114: aload 5
/* 66:   */     //   116: ldc 26
/* 67:   */     //   118: new 27	java/lang/StringBuilder
/* 68:   */     //   121: dup
/* 69:   */     //   122: invokespecial 28	java/lang/StringBuilder:<init>	()V
/* 70:   */     //   125: ldc 29
/* 71:   */     //   127: invokevirtual 30	java/lang/StringBuilder:append	(Ljava/lang/String;)Ljava/lang/StringBuilder;
/* 72:   */     //   130: aload 6
/* 73:   */     //   132: invokevirtual 31	java/lang/Exception:toString	()Ljava/lang/String;
/* 74:   */     //   135: invokevirtual 30	java/lang/StringBuilder:append	(Ljava/lang/String;)Ljava/lang/StringBuilder;
/* 75:   */     //   138: invokevirtual 32	java/lang/StringBuilder:toString	()Ljava/lang/String;
/* 76:   */     //   141: invokevirtual 17	org/json/simple/JSONObject:put	(Ljava/lang/Object;Ljava/lang/Object;)Ljava/lang/Object;
/* 77:   */     //   144: pop
/* 78:   */     //   145: aload 5
/* 79:   */     //   147: ldc 33
/* 80:   */     //   149: aload 6
/* 81:   */     //   151: invokevirtual 22	java/lang/Exception:getMessage	()Ljava/lang/String;
/* 82:   */     //   154: invokevirtual 17	org/json/simple/JSONObject:put	(Ljava/lang/Object;Ljava/lang/Object;)Ljava/lang/Object;
/* 83:   */     //   157: pop
/* 84:   */     //   158: aload 5
/* 85:   */     //   160: areturn
/* 86:   */     // Line number table:
/* 87:   */     //   Java source line #24	-> byte code offset #0
/* 88:   */     //   Java source line #25	-> byte code offset #12
/* 89:   */     //   Java source line #26	-> byte code offset #24
/* 90:   */     //   Java source line #27	-> byte code offset #31
/* 91:   */     //   Java source line #29	-> byte code offset #40
/* 92:   */     //   Java source line #30	-> byte code offset #47
/* 93:   */     //   Java source line #31	-> byte code offset #57
/* 94:   */     //   Java source line #32	-> byte code offset #72
/* 95:   */     //   Java source line #38	-> byte code offset #87
/* 96:   */     //   Java source line #33	-> byte code offset #90
/* 97:   */     //   Java source line #34	-> byte code offset #92
/* 98:   */     //   Java source line #35	-> byte code offset #102
/* 99:   */     //   Java source line #36	-> byte code offset #114
/* :0:   */     //   Java source line #37	-> byte code offset #145
/* :1:   */     //   Java source line #39	-> byte code offset #158
/* :2:   */     // Local variable table:
/* :3:   */     //   start	length	slot	name	signature
/* :4:   */     //   0	161	0	this	BroadcastTransaction
/* :5:   */     //   0	161	1	paramHttpServletRequest	javax.servlet.http.HttpServletRequest
/* :6:   */     //   11	14	2	str1	String
/* :7:   */     //   23	3	3	str2	String
/* :8:   */     //   29	48	4	localTransaction	nxt.Transaction
/* :9:   */     //   38	121	5	localJSONObject	org.json.simple.JSONObject
/* ;0:   */     //   90	60	6	localValidationException	nxt.NxtException.ValidationException
/* ;1:   */     // Exception table:
/* ;2:   */     //   from	to	target	type
/* ;3:   */     //   40	87	90	nxt/NxtException$ValidationException
/* ;4:   */     //   40	87	90	java/lang/RuntimeException
/* ;5:   */   }
/* ;6:   */   
/* ;7:   */   boolean requirePost()
/* ;8:   */   {
/* ;9:45 */     return true;
/* <0:   */   }
/* <1:   */ }


/* Location:           E:\java decompi;er\burst.jar
 * Qualified Name:     nxt.http.BroadcastTransaction
 * JD-Core Version:    0.7.1
 */